{
  "last_updated": "2026-01-18 11:43:32",
  "total_scanned": 16,
  "top_alerts_count": 15,
  "alerts_by_strategy": {
    "Bear Put Spread": 4,
    "Bull Call Spread": 2,
    "Long Put": 2,
    "Long Call": 4,
    "Long Straddle": 3,
    "Long Strangle": 1
  },
  "top_alerts": [
    {
      "timestamp": "2026-01-18 11:43:27",
      "symbol": "NIFTY",
      "instrument_type": "INDEX",
      "strategy": "Bear Put Spread",
      "strike": "25700/25600",
      "premium": 37.9,
      "price_source": "spread",
      "spot": 25699.15,
      "volume": 16307325,
      "open_interest": 95679,
      "iv": 11.37,
      "iv_percentile": 29,
      "expiry": "20-Jan-2026",
      "days_to_expiry": 2,
      "lot_size": 25,
      "total_cost": 947.5,
      "breakeven": 25662.1,
      "distance_from_spot": "-0.4%",
      "leg1": {
        "strike": 25700,
        "premium": 90,
        "action": "BUY"
      },
      "leg2": {
        "strike": 25600,
        "premium": 52.1,
        "action": "SELL"
      },
      "max_profit": 1552.5,
      "max_loss": 947.5,
      "reward_ratio": 1.64
    },
    {
      "timestamp": "2026-01-18 11:43:27",
      "symbol": "NIFTY",
      "instrument_type": "INDEX",
      "strategy": "Bull Call Spread",
      "strike": "25700/25800",
      "premium": 44.4,
      "price_source": "spread",
      "spot": 25699.15,
      "volume": 13906421,
      "open_interest": 131180,
      "iv": 11.37,
      "iv_percentile": 29,
      "expiry": "20-Jan-2026",
      "days_to_expiry": 2,
      "lot_size": 25,
      "total_cost": 1110.0,
      "breakeven": 25744.4,
      "distance_from_spot": "+0.4%",
      "leg1": {
        "strike": 25700,
        "premium": 108.45,
        "action": "BUY"
      },
      "leg2": {
        "strike": 25800,
        "premium": 64.05,
        "action": "SELL"
      },
      "max_profit": 1390.0,
      "max_loss": 1110.0,
      "reward_ratio": 1.25
    },
    {
      "timestamp": "2026-01-18 11:43:27",
      "symbol": "NIFTY",
      "instrument_type": "INDEX",
      "strategy": "Long Put",
      "strike": 25700,
      "premium": 89.65,
      "price_source": "ltp",
      "spot": 25699.15,
      "volume": 10280508,
      "open_interest": 105679,
      "iv": 11.37,
      "iv_percentile": 29,
      "expiry": "20-Jan-2026",
      "days_to_expiry": 2,
      "lot_size": 25,
      "total_cost": 2241.25,
      "breakeven": 25610.35,
      "distance_from_spot": "+0.0% ITM"
    },
    {
      "timestamp": "2026-01-18 11:43:27",
      "symbol": "NIFTY",
      "instrument_type": "INDEX",
      "strategy": "Long Call",
      "strike": 25800,
      "premium": 64.1,
      "price_source": "ltp",
      "spot": 25699.15,
      "volume": 8301931,
      "open_interest": 193159,
      "iv": 11.37,
      "iv_percentile": 29,
      "expiry": "20-Jan-2026",
      "days_to_expiry": 2,
      "lot_size": 25,
      "total_cost": 1602.5,
      "breakeven": 25864.1,
      "distance_from_spot": "+0.4% OTM"
    },
    {
      "timestamp": "2026-01-18 11:43:27",
      "symbol": "NIFTY",
      "instrument_type": "INDEX",
      "strategy": "Long Put",
      "strike": 25800,
      "premium": 144.55,
      "price_source": "ltp",
      "spot": 25699.15,
      "volume": 6938209,
      "open_interest": 82127,
      "iv": 11.37,
      "iv_percentile": 29,
      "expiry": "20-Jan-2026",
      "days_to_expiry": 2,
      "lot_size": 25,
      "total_cost": 3613.75,
      "breakeven": 25655.45,
      "distance_from_spot": "+0.4% ITM"
    },
    {
      "timestamp": "2026-01-18 11:43:27",
      "symbol": "NIFTY",
      "instrument_type": "INDEX",
      "strategy": "Long Call",
      "strike": 25700,
      "premium": 108.45,
      "price_source": "ltp",
      "spot": 25699.15,
      "volume": 5604490,
      "open_interest": 131180,
      "iv": 11.37,
      "iv_percentile": 29,
      "expiry": "20-Jan-2026",
      "days_to_expiry": 2,
      "lot_size": 25,
      "total_cost": 2711.25,
      "breakeven": 25808.45,
      "distance_from_spot": "+0.0% OTM"
    },
    {
      "timestamp": "2026-01-18 11:43:27",
      "symbol": "NIFTY",
      "instrument_type": "INDEX",
      "strategy": "Long Call",
      "strike": 25850,
      "premium": 47.95,
      "price_source": "ltp",
      "spot": 25699.15,
      "volume": 5400623,
      "open_interest": 103747,
      "iv": 11.37,
      "iv_percentile": 29,
      "expiry": "20-Jan-2026",
      "days_to_expiry": 2,
      "lot_size": 25,
      "total_cost": 1198.75,
      "breakeven": 25897.95,
      "distance_from_spot": "+0.6% OTM"
    },
    {
      "timestamp": "2026-01-18 11:43:27",
      "symbol": "NIFTY",
      "instrument_type": "INDEX",
      "strategy": "Long Call",
      "strike": 25750,
      "premium": 84.0,
      "price_source": "ltp",
      "spot": 25699.15,
      "volume": 5213902,
      "open_interest": 95748,
      "iv": 11.37,
      "iv_percentile": 29,
      "expiry": "20-Jan-2026",
      "days_to_expiry": 2,
      "lot_size": 25,
      "total_cost": 2100.0,
      "breakeven": 25834.0,
      "distance_from_spot": "+0.2% OTM"
    },
    {
      "timestamp": "2026-01-18 11:43:28",
      "symbol": "BANKNIFTY",
      "instrument_type": "INDEX",
      "strategy": "Long Straddle",
      "strike": 60100,
      "premium": 925.0,
      "price_source": "straddle",
      "spot": 60110.5,
      "volume": 226205,
      "open_interest": 9301,
      "iv": 11.99,
      "iv_percentile": 33,
      "expiry": "27-Jan-2026",
      "days_to_expiry": 9,
      "lot_size": 15,
      "total_cost": 13875.0,
      "breakeven": "59175/61025",
      "distance_from_spot": "\u00b11.5% to breakeven",
      "leg1": {
        "strike": 60100,
        "premium": 510.75,
        "action": "BUY CE"
      },
      "leg2": {
        "strike": 60100,
        "premium": 414.25,
        "action": "BUY PE"
      },
      "max_loss": 13875.0
    },
    {
      "timestamp": "2026-01-18 11:43:28",
      "symbol": "BANKNIFTY",
      "instrument_type": "INDEX",
      "strategy": "Bear Put Spread",
      "strike": "60100/59900",
      "premium": 83.45,
      "price_source": "spread",
      "spot": 60110.5,
      "volume": 188340,
      "open_interest": 7718,
      "iv": 11.99,
      "iv_percentile": 33,
      "expiry": "27-Jan-2026",
      "days_to_expiry": 9,
      "lot_size": 15,
      "total_cost": 1251.75,
      "breakeven": 60016.55,
      "distance_from_spot": "-0.4%",
      "leg1": {
        "strike": 60100,
        "premium": 414.25,
        "action": "BUY"
      },
      "leg2": {
        "strike": 59900,
        "premium": 330.8,
        "action": "SELL"
      },
      "max_profit": 1748.25,
      "max_loss": 1251.75,
      "reward_ratio": 1.4
    },
    {
      "timestamp": "2026-01-18 11:43:28",
      "symbol": "BANKNIFTY",
      "instrument_type": "INDEX",
      "strategy": "Bull Call Spread",
      "strike": "60100/60300",
      "premium": 105.15,
      "price_source": "spread",
      "spot": 60110.5,
      "volume": 180472,
      "open_interest": 10655,
      "iv": 11.99,
      "iv_percentile": 33,
      "expiry": "27-Jan-2026",
      "days_to_expiry": 9,
      "lot_size": 15,
      "total_cost": 1577.25,
      "breakeven": 60205.15,
      "distance_from_spot": "+0.3%",
      "leg1": {
        "strike": 60100,
        "premium": 510.75,
        "action": "BUY"
      },
      "leg2": {
        "strike": 60300,
        "premium": 405.6,
        "action": "SELL"
      },
      "max_profit": 1422.75,
      "max_loss": 1577.25,
      "reward_ratio": 0.9
    },
    {
      "timestamp": "2026-01-18 11:43:32",
      "symbol": "BAJFINANCE",
      "instrument_type": "STOCK",
      "strategy": "Long Straddle",
      "strike": 950,
      "premium": 27.8,
      "price_source": "straddle",
      "spot": 950.25,
      "volume": 10449,
      "open_interest": 1409,
      "iv": 12.87,
      "iv_percentile": 0,
      "expiry": "27-Jan-2026",
      "days_to_expiry": 9,
      "lot_size": 125,
      "total_cost": 3475.0,
      "breakeven": "922/978",
      "distance_from_spot": "\u00b12.9% to breakeven",
      "leg1": {
        "strike": 950,
        "premium": 14.8,
        "action": "BUY CE"
      },
      "leg2": {
        "strike": 950,
        "premium": 13,
        "action": "BUY PE"
      },
      "max_loss": 3475.0
    },
    {
      "timestamp": "2026-01-18 11:43:32",
      "symbol": "BAJFINANCE",
      "instrument_type": "STOCK",
      "strategy": "Long Strangle",
      "strike": "940/960",
      "premium": 19.25,
      "price_source": "strangle",
      "spot": 950.25,
      "volume": 9575,
      "open_interest": 1105,
      "iv": 12.87,
      "iv_percentile": 0,
      "expiry": "27-Jan-2026",
      "days_to_expiry": 9,
      "lot_size": 125,
      "total_cost": 2406.25,
      "breakeven": "921/979",
      "distance_from_spot": "\u00b13.1% to breakeven",
      "leg1": {
        "strike": 960,
        "premium": 10.45,
        "action": "BUY CE"
      },
      "leg2": {
        "strike": 940,
        "premium": 8.8,
        "action": "BUY PE"
      },
      "max_loss": 2406.25
    },
    {
      "timestamp": "2026-01-18 11:43:32",
      "symbol": "BAJFINANCE",
      "instrument_type": "STOCK",
      "strategy": "Bear Put Spread",
      "strike": "950/940",
      "premium": 4.4,
      "price_source": "spread",
      "spot": 950.25,
      "volume": 6650,
      "open_interest": 1105,
      "iv": 12.87,
      "iv_percentile": 0,
      "expiry": "27-Jan-2026",
      "days_to_expiry": 9,
      "lot_size": 125,
      "total_cost": 550.0,
      "breakeven": 945.6,
      "distance_from_spot": "-1.1%",
      "leg1": {
        "strike": 950,
        "premium": 13,
        "action": "BUY"
      },
      "leg2": {
        "strike": 940,
        "premium": 8.6,
        "action": "SELL"
      },
      "max_profit": 700.0,
      "max_loss": 550.0,
      "reward_ratio": 1.27
    },
    {
      "timestamp": "2026-01-18 11:43:30",
      "symbol": "ADANIENT",
      "instrument_type": "STOCK",
      "strategy": "Long Straddle",
      "strike": 2160,
      "premium": 78.6,
      "price_source": "straddle",
      "spot": 2157.3,
      "volume": 3376,
      "open_interest": 702,
      "iv": 28.31,
      "iv_percentile": 34,
      "expiry": "27-Jan-2026",
      "days_to_expiry": 9,
      "lot_size": 250,
      "total_cost": 19650.0,
      "breakeven": "2081/2239",
      "distance_from_spot": "\u00b13.6% to breakeven",
      "leg1": {
        "strike": 2160,
        "premium": 40,
        "action": "BUY CE"
      },
      "leg2": {
        "strike": 2160,
        "premium": 38.6,
        "action": "BUY PE"
      },
      "max_loss": 19650.0
    }
  ]
}